think_mcp/__init__.py
think_mcp/__main__.py
think_mcp-0.1.16.dist-info/licenses/LICENSE
think_mcp-0.1.16.dist-info/METADATA
think_mcp-0.1.16.dist-info/WHEEL
think_mcp-0.1.16.dist-info/entry_points.txt
think_mcp-0.1.16.dist-info/top_level.txt
think_mcp-0.1.16.dist-info/RECORD
