Metadata-Version: 2.4
Name: think_mcp
Version: 0.1.16
Summary: MCP server providing a 'think' tool for structured reasoning, inspired by Anthropic's Claude 'think' tool. Enables agentic LLMs to pause, log thoughts, and improve multi-step tool use.
Author-email: Konstantin Krestnikov <k.krestnikov@gmail.com>
License: MIT
Project-URL: Homepage, https://github.com/Rai220/think-mcp
Keywords: mcp,think,agentic,llm,structured reasoning,anthropic,claude
Requires-Python: >=3.10
License-File: LICENSE
Requires-Dist: mcp[cli]>=1.6.0
Requires-Dist: python-dotenv>=1.1.0
Requires-Dist: tavily-python>=0.5.4
Dynamic: license-file
